README.md
setup.py
timer.py
excel_productive_CLI.egg-info/PKG-INFO
excel_productive_CLI.egg-info/SOURCES.txt
excel_productive_CLI.egg-info/dependency_links.txt
excel_productive_CLI.egg-info/entry_points.txt
excel_productive_CLI.egg-info/requires.txt
excel_productive_CLI.egg-info/top_level.txt