Metadata-Version: 2.1
Name: excel-productive-CLI
Version: 4.3.0
Summary: TimeTracker-CLI is a command-line interface (CLI) application designed to help users efficiently track and manage their time spent on various tasks and projects.
Home-page: https://github.com/nahid25/CLI-Excel-Productive-tool
Author: Nahidul Ekon
Author-email: nahidekon314@gmail.com
Classifier: Programming Language :: Python :: 3
Classifier: License :: OSI Approved :: MIT License
Classifier: Operating System :: OS Independent
Requires-Dist: pyfiglet
Requires-Dist: tqdm
Requires-Dist: inquirer
Requires-Dist: yaspin
Requires-Dist: rich
